packaage/__init__.py
search_recommend_system-0.0.0.0.1.dist-info/LICENSE.txt
search_recommend_system-0.0.0.0.1.dist-info/METADATA
search_recommend_system-0.0.0.0.1.dist-info/WHEEL
search_recommend_system-0.0.0.0.1.dist-info/top_level.txt
search_recommend_system-0.0.0.0.1.dist-info/RECORD
