Metadata-Version: 2.1
Name: search-recommend-system
Version: 0.0.0.0.1
Summary: <Basic desc>
Author: neeraj03
Author-email: neerajjoshi9560562571@gmail.com
Classifier: Programming Language :: Python :: 3
Classifier: License :: OSI Approved :: MIT License
Classifier: Operating System :: OS Independent
License-File: LICENSE.txt
Requires-Dist: annoy
Requires-Dist: pandas
Requires-Dist: numpy
Requires-Dist: scikit-learn
